cesarp/SIA2024/CSVYFileDumper.py
cesarp/SIA2024/NullParametersFactory.py
cesarp/SIA2024/SIA2024BuildingType.py
cesarp/SIA2024/SIA2024DataAccessor.py
cesarp/SIA2024/SIA2024Facade.py
cesarp/SIA2024/SIA2024Parameters.py
cesarp/SIA2024/SIA2024ParametersFactory.py
cesarp/SIA2024/SIA2024ParamsManager.py
cesarp/SIA2024/SIA2024_2016_RoomType.py
cesarp/SIA2024/__init__.py
cesarp/SIA2024/demand_generators/ActivityHeatGainCalculator.py
cesarp/SIA2024/demand_generators/AppliancesDemandGenerator.py
cesarp/SIA2024/demand_generators/AreaPerPersonCalculator.py
cesarp/SIA2024/demand_generators/BuildingTypeProtocol.py
cesarp/SIA2024/demand_generators/DHWDemandBasedOnLiterPerDayGenerator.py
cesarp/SIA2024/demand_generators/DHWDemandGenerator.py
cesarp/SIA2024/demand_generators/InfiltrationRateGenerator.py
cesarp/SIA2024/demand_generators/LightingDemandGenerator.py
cesarp/SIA2024/demand_generators/NighttimePatternGenerator.py
cesarp/SIA2024/demand_generators/OccupancyProfileGenerator.py
cesarp/SIA2024/demand_generators/ThermostatDemandGenerator.py
cesarp/SIA2024/demand_generators/ValuePerKeyCache.py
cesarp/SIA2024/demand_generators/VariationMonthly.py
cesarp/SIA2024/demand_generators/VentilationDemandGenerator.py
cesarp/SIA2024/demand_generators/__init__.py
cesarp/SIA2024/generated_params/nominal/SIA2024_ASSEMBLY_HALL_nominal.csvy
cesarp/SIA2024/generated_params/nominal/SIA2024_HOSPITAL_nominal.csvy
cesarp/SIA2024/generated_params/nominal/SIA2024_INDUSTRY_nominal.csvy
cesarp/SIA2024/generated_params/nominal/SIA2024_MFH_nominal.csvy
cesarp/SIA2024/generated_params/nominal/SIA2024_OFFICE_nominal.csvy
cesarp/SIA2024/generated_params/nominal/SIA2024_RESTAURANT_nominal.csvy
cesarp/SIA2024/generated_params/nominal/SIA2024_SCHOOL_nominal.csvy
cesarp/SIA2024/generated_params/nominal/SIA2024_SFH_nominal.csvy
cesarp/SIA2024/generated_params/nominal/SIA2024_SHOP_nominal.csvy
cesarp/SIA2024/generated_params/nominal/SIA2024_SPORTS_BUILDING_nominal.csvy
cesar_p-2.4.0.dist-info/LICENSE
cesar_p-2.4.0.dist-info/METADATA
cesar_p-2.4.0.dist-info/WHEEL
cesar_p-2.4.0.dist-info/RECORD
